asciicon/__init__.py
asciicon/cli.py
asciicon/icons/eastern/color/christ.txt
asciicon/icons/eastern/color/mary.txt
asciicon/icons/eastern/color/trinity.txt
asciicon/icons/eastern/mono/christ.txt
asciicon/icons/eastern/mono/mary.txt
asciicon/icons/eastern/mono/trinity.txt
asciicon/prayers/holy_spirit.txt
asciicon/prayers/icon_of_christ.txt
asciicon/prayers/jesus.txt
asciicon/prayers/our_father.txt
asciicon/prayers/trisagion.txt
asciicon-1.0.4.dist-info/LICENSE
asciicon-1.0.4.dist-info/METADATA
asciicon-1.0.4.dist-info/WHEEL
asciicon-1.0.4.dist-info/entry_points.txt
asciicon-1.0.4.dist-info/top_level.txt
asciicon-1.0.4.dist-info/RECORD
